code_flowchart/__init__.py
code_flowchart/cli.py
code_flowchart/generator.py
tests/__init__.py
tests/test_generator.py
code_flowchart-0.2.0.dist-info/LICENSE
code_flowchart-0.2.0.dist-info/METADATA
code_flowchart-0.2.0.dist-info/WHEEL
code_flowchart-0.2.0.dist-info/entry_points.txt
code_flowchart-0.2.0.dist-info/top_level.txt
code_flowchart-0.2.0.dist-info/RECORD
