Metadata-Version: 2.2
Name: code_flowchart
Version: 0.2.0
Summary: A simple tool for creating flowcharts of code
Home-page: https://github.com/16st58/code-flowchart
Author: 16st58
Author-email: kithree1010@gmail.com
Classifier: Programming Language :: Python :: 3
Classifier: Operating System :: OS Independent
Requires-Python: >=3.9
License-File: LICENSE
Requires-Dist: graphviz
Dynamic: author
Dynamic: author-email
Dynamic: classifier
Dynamic: description
Dynamic: description-content-type
Dynamic: home-page
Dynamic: requires-dist
Dynamic: requires-python
Dynamic: summary
